{
	"song": {
		"player1": "tails doll play",
		"sectionLengths": [],
		"events": [],
		"gfVersion": "gf",
		"notes": [
			{
				"typeOfSection": 0,
				"lengthInSteps": 16,
				"sectionNotes": [
					[
						441.176470588235,
						2,
						0
					],
					[
						661.764705882353,
						3,
						0
					],
					[
						772.058823529412,
						2,
						0
					],
					[
						992.647058823529,
						0,
						0
					]
				],
				"altAnim": false,
				"bpm": 132,
				"mustHitSection": false,
				"changeBPM": false
			},
			{
				"typeOfSection": 0,
				"lengthInSteps": 16,
				"sectionNotes": [
					[
						1764.70588235294,
						3,
						145.588235294118
					],
					[
						2316.17647058824,
						2,
						185.294117647059
					],
					[
						2647.05882352941,
						1,
						0
					],
					[
						2757.35294117647,
						2,
						220.588235294118
					],
					[
						3088.23529411765,
						3,
						110.294117647059
					],
					[
						3419.11764705882,
						0,
						0
					]
				],
				"altAnim": false,
				"bpm": 132,
				"mustHitSection": false,
				"changeBPM": false
			},
			{
				"typeOfSection": 0,
				"lengthInSteps": 16,
				"sectionNotes": [
					[
						3639.70588235294,
						2,
						110.294117647059
					],
					[
						3970.58823529412,
						1,
						0
					],
					[
						4080.88235294118,
						0,
						0
					],
					[
						4632.35294117647,
						3,
						0
					],
					[
						4742.64705882353,
						0,
						0
					],
					[
						4963.23529411765,
						2,
						220.588235294118
					],
					[
						4411.76470588235,
						1,
						0
					],
					[
						4466.91176470588,
						2,
						0
					]
				],
				"altAnim": false,
				"bpm": 132,
				"mustHitSection": false,
				"changeBPM": false
			},
			{
				"typeOfSection": 0,
				"lengthInSteps": 16,
				"sectionNotes": [
					[
						5294.11764705882,
						2,
						0
					],
					[
						5404.41176470588,
						3,
						0
					],
					[
						5955.88235294118,
						3,
						0
					],
					[
						6066.17647058824,
						1,
						0
					],
					[
						6286.76470588235,
						2,
						0
					],
					[
						6397.05882352941,
						1,
						0
					],
					[
						6617.64705882353,
						0,
						0
					],
					[
						6727.94117647059,
						2,
						0
					],
					[
						5625,
						0,
						0
					],
					[
						5735.29411764706,
						2,
						0
					],
					[
						6948.52941176471,
						3,
						0
					]
				],
				"altAnim": false,
				"bpm": 132,
				"mustHitSection": true,
				"changeBPM": false
			},
			{
				"typeOfSection": 0,
				"lengthInSteps": 16,
				"sectionNotes": [
					[
						7058.82352941176,
						2,
						0
					],
					[
						7279.41176470588,
						1,
						0
					],
					[
						7389.70588235294,
						2,
						0
					],
					[
						7610.29411764706,
						0,
						220.588235294118
					],
					[
						7941.17647058824,
						3,
						0
					],
					[
						8051.47058823529,
						2,
						0
					],
					[
						8382.35294117647,
						2,
						0
					],
					[
						8272.05882352941,
						1,
						0
					],
					[
						8602.94117647059,
						1,
						0
					],
					[
						8713.23529411765,
						0,
						0
					],
					[
						8602.94117647059,
						6,
						0
					],
					[
						8713.23529411765,
						5,
						0
					],
					[
						8272.05882352941,
						4,
						0
					],
					[
						8382.35294117647,
						7,
						0
					],
					[
						7941.17647058824,
						7,
						0
					],
					[
						8051.47058823529,
						6,
						0
					]
				],
				"altAnim": false,
				"bpm": 132,
				"mustHitSection": true,
				"changeBPM": false
			},
			{
				"typeOfSection": 0,
				"lengthInSteps": 16,
				"sectionNotes": [
					[
						9705.88235294118,
						5,
						0
					],
					[
						9926.47058823529,
						7,
						0
					],
					[
						10257.3529411765,
						6,
						220.588235294118
					],
					[
						8933.82352941177,
						3,
						0
					],
					[
						9044.11764705882,
						1,
						0
					],
					[
						9264.70588235294,
						2,
						0
					],
					[
						9705.88235294118,
						1,
						0
					],
					[
						9926.47058823529,
						3,
						0
					],
					[
						10036.7647058824,
						1,
						0
					],
					[
						9375,
						3,
						0
					],
					[
						9595.58823529412,
						2,
						0
					],
					[
						9761.02941176471,
						0,
						0
					],
					[
						10257.3529411765,
						2,
						220.588235294118
					],
					[
						8933.82352941177,
						4,
						0
					],
					[
						9044.11764705882,
						5,
						0
					],
					[
						9264.70588235294,
						6,
						0
					],
					[
						9375,
						7,
						0
					],
					[
						9595.58823529412,
						6,
						0
					],
					[
						9761.02941176471,
						4,
						0
					],
					[
						10036.7647058824,
						5,
						0
					]
				],
				"altAnim": false,
				"bpm": 132,
				"mustHitSection": true,
				"changeBPM": false
			},
			{
				"typeOfSection": 0,
				"lengthInSteps": 16,
				"sectionNotes": [
					[
						10588.2352941176,
						1,
						0
					],
					[
						10698.5294117647,
						0,
						0
					],
					[
						10919.1176470588,
						2,
						0
					],
					[
						11029.4117647059,
						3,
						0
					],
					[
						11250,
						2,
						0
					],
					[
						11360.2941176471,
						1,
						0
					],
					[
						11580.8823529412,
						0,
						0
					]
				],
				"altAnim": false,
				"bpm": 132,
				"mustHitSection": false,
				"changeBPM": false
			},
			{
				"typeOfSection": 0,
				"lengthInSteps": 16,
				"sectionNotes": [
					[
						12352.9411764706,
						2,
						110.294117647059
					],
					[
						12683.8235294118,
						3,
						0
					],
					[
						12904.4117647059,
						2,
						220.588235294118
					],
					[
						13235.2941176471,
						1,
						0
					],
					[
						13345.5882352941,
						0,
						220.588235294118
					],
					[
						13676.4705882353,
						3,
						110.294117647059
					],
					[
						14007.3529411765,
						2,
						0
					]
				],
				"altAnim": false,
				"bpm": 132,
				"mustHitSection": false,
				"changeBPM": false
			},
			{
				"typeOfSection": 0,
				"lengthInSteps": 16,
				"sectionNotes": [
					[
						14227.9411764706,
						3,
						0
					],
					[
						14558.8235294118,
						0,
						0
					],
					[
						14669.1176470588,
						2,
						220.588235294118
					],
					[
						15000,
						1,
						0
					],
					[
						15055.1470588235,
						2,
						0
					],
					[
						15220.5882352941,
						1,
						0
					],
					[
						15330.8823529412,
						0,
						0
					],
					[
						15551.4705882353,
						3,
						220.588235294118
					]
				],
				"altAnim": false,
				"bpm": 132,
				"mustHitSection": false,
				"changeBPM": false
			},
			{
				"typeOfSection": 0,
				"lengthInSteps": 16,
				"sectionNotes": [
					[
						15882.3529411765,
						2,
						0
					],
					[
						15992.6470588235,
						3,
						0
					],
					[
						16654.4117647059,
						1,
						0
					],
					[
						17316.1764705882,
						2,
						0
					],
					[
						17536.7647058824,
						3,
						0
					],
					[
						16213.2352941176,
						2,
						0
					],
					[
						16323.5294117647,
						0,
						0
					],
					[
						16544.1176470588,
						2,
						0
					],
					[
						16875,
						0,
						0
					],
					[
						16875,
						3,
						0
					],
					[
						17205.8823529412,
						2,
						0
					]
				],
				"altAnim": false,
				"bpm": 132,
				"mustHitSection": true,
				"changeBPM": false
			},
			{
				"typeOfSection": 0,
				"lengthInSteps": 16,
				"sectionNotes": [
					[
						17647.0588235294,
						2,
						0
					],
					[
						17867.6470588235,
						1,
						0
					],
					[
						18639.7058823529,
						2,
						0
					],
					[
						17702.2058823529,
						0,
						0
					],
					[
						17977.9411764706,
						3,
						0
					],
					[
						18198.5294117647,
						2,
						220.588235294118
					],
					[
						18529.4117647059,
						1,
						0
					],
					[
						18970.5882352941,
						0,
						330.882352941176
					],
					[
						18970.5882352941,
						4,
						330.882352941176
					]
				],
				"altAnim": false,
				"bpm": 132,
				"mustHitSection": true,
				"changeBPM": false
			},
			{
				"typeOfSection": 0,
				"lengthInSteps": 16,
				"sectionNotes": [
					[
						19632.3529411765,
						1,
						330.882352941176
					],
					[
						20294.1176470588,
						3,
						0
					],
					[
						20514.7058823529,
						2,
						0
					],
					[
						20845.5882352941,
						1,
						220.588235294118
					],
					[
						19632.3529411765,
						7,
						330.882352941176
					],
					[
						20294.1176470588,
						6,
						0
					],
					[
						20514.7058823529,
						5,
						0
					],
					[
						20845.5882352941,
						4,
						220.588235294118
					]
				],
				"altAnim": false,
				"bpm": 132,
				"mustHitSection": true,
				"changeBPM": false
			},
			{
				"typeOfSection": 0,
				"lengthInSteps": 16,
				"sectionNotes": [
					[
						21176.4705882353,
						4,
						0
					],
					[
						21286.7647058823,
						5,
						0
					],
					[
						21507.3529411765,
						6,
						0
					],
					[
						21617.6470588235,
						5,
						330.882352941176
					],
					[
						21176.4705882353,
						2,
						0
					],
					[
						21286.7647058823,
						3,
						0
					],
					[
						21507.3529411765,
						2,
						0
					],
					[
						21948.5294117647,
						0,
						110.294117647059
					],
					[
						22500,
						1,
						110.294117647059
					],
					[
						22279.4117647059,
						2,
						0
					],
					[
						22830.8823529412,
						0,
						0
					]
				],
				"sectionBeats": 4,
				"altAnim": false,
				"bpm": 132,
				"mustHitSection": false,
				"changeBPM": false
			},
			{
				"typeOfSection": 0,
				"lengthInSteps": 16,
				"sectionNotes": [
					[
						22941.1764705882,
						2,
						110.294117647059
					],
					[
						23823.5294117647,
						6,
						0
					],
					[
						23933.8235294118,
						7,
						0
					],
					[
						24154.4117647059,
						4,
						0
					],
					[
						24264.7058823529,
						6,
						330.882352941176
					],
					[
						23272.0588235294,
						3,
						0
					],
					[
						23492.6470588235,
						0,
						551.470588235294
					],
					[
						24595.5882352941,
						0,
						110.294117647059
					]
				],
				"sectionBeats": 4,
				"altAnim": false,
				"bpm": 132,
				"mustHitSection": false,
				"changeBPM": false
			},
			{
				"typeOfSection": 0,
				"lengthInSteps": 16,
				"sectionNotes": [
					[
						24926.4705882353,
						1,
						0
					],
					[
						25147.0588235294,
						1,
						110.294117647059
					],
					[
						25477.9411764706,
						2,
						0
					],
					[
						25588.2352941176,
						3,
						0
					],
					[
						25919.1176470588,
						0,
						0
					],
					[
						26139.7058823529,
						2,
						441.176470588235
					]
				],
				"sectionBeats": 4,
				"altAnim": false,
				"bpm": 132,
				"mustHitSection": false,
				"changeBPM": false
			},
			{
				"sectionBeats": 4,
				"typeOfSection": 0,
				"lengthInSteps": 16,
				"sectionNotes": [
					[
						26470.5882352941,
						2,
						0
					],
					[
						26580.8823529412,
						3,
						0
					],
					[
						26801.4705882353,
						0,
						0
					],
					[
						27242.6470588235,
						2,
						0
					],
					[
						27573.5294117647,
						3,
						0
					],
					[
						27794.1176470588,
						2,
						110.294117647059
					],
					[
						28125,
						1,
						0
					]
				],
				"altAnim": false,
				"bpm": 132,
				"mustHitSection": true,
				"changeBPM": false
			},
			{
				"sectionBeats": 4,
				"altAnim": false,
				"mustHitSection": true,
				"sectionNotes": [
					[
						29558.8235294118,
						6,
						330.882352941176
					],
					[
						28566.1764705882,
						3,
						0
					],
					[
						28235.2941176471,
						0,
						110.294117647059
					],
					[
						28786.7647058823,
						1,
						661.764705882353
					],
					[
						29117.6470588235,
						5,
						0
					],
					[
						29227.9411764706,
						6,
						0
					],
					[
						29448.5294117647,
						7,
						0
					],
					[
						29889.7058823529,
						2,
						110.294117647059
					]
				],
				"lengthInSteps": 16,
				"typeOfSection": 0,
				"gfSection": false,
				"changeBPM": false,
				"bpm": 132
			},
			{
				"typeOfSection": 0,
				"lengthInSteps": 16,
				"sectionNotes": [
					[
						30220.5882352941,
						3,
						0
					],
					[
						30441.1764705882,
						2,
						110.294117647059
					],
					[
						30772.0588235294,
						1,
						0
					],
					[
						30882.3529411765,
						0,
						0
					],
					[
						31213.2352941176,
						2,
						0
					],
					[
						31433.8235294118,
						1,
						661.764705882353
					]
				],
				"altAnim": false,
				"gfSection": false,
				"bpm": 132,
				"mustHitSection": true,
				"changeBPM": false
			},
			{
				"typeOfSection": 0,
				"lengthInSteps": 16,
				"sectionNotes": [
					[
						31764.7058823529,
						6,
						110.294117647059
					],
					[
						32095.5882352941,
						5,
						0
					],
					[
						32205.8823529412,
						4,
						110.294117647059
					],
					[
						32536.7647058823,
						7,
						110.294117647059
					],
					[
						32867.6470588235,
						5,
						110.294117647059
					],
					[
						32536.7647058823,
						0,
						110.294117647059
					],
					[
						32867.6470588235,
						1,
						0
					],
					[
						33088.2352941176,
						3,
						110.294117647059
					],
					[
						33419.1176470588,
						2,
						0
					]
				],
				"altAnim": false,
				"gfSection": false,
				"bpm": 132,
				"mustHitSection": true,
				"changeBPM": false
			},
			{
				"typeOfSection": 0,
				"lengthInSteps": 16,
				"sectionNotes": [
					[
						33529.4117647059,
						5,
						110.294117647059
					],
					[
						33860.294117647,
						4,
						0
					],
					[
						34080.8823529412,
						5,
						661.764705882353
					],
					[
						35183.8235294118,
						7,
						110.294117647059
					],
					[
						33860.294117647,
						2,
						0
					],
					[
						34080.8823529412,
						1,
						220.588235294118
					],
					[
						35183.8235294118,
						0,
						220.588235294118
					],
					[
						34411.7647058823,
						2,
						0
					],
					[
						34742.6470588235,
						0,
						0
					],
					[
						34522.0588235294,
						3,
						0
					],
					[
						34852.9411764706,
						2,
						0
					],
					[
						35073.5294117647,
						1,
						0
					]
				],
				"altAnim": false,
				"gfSection": false,
				"bpm": 132,
				"mustHitSection": false,
				"changeBPM": false
			},
			{
				"typeOfSection": 0,
				"lengthInSteps": 16,
				"sectionNotes": [
					[
						35514.7058823529,
						7,
						220.588235294118
					],
					[
						35514.7058823529,
						2,
						0
					],
					[
						35735.2941176471,
						2,
						110.294117647059
					],
					[
						36176.4705882353,
						2,
						110.294117647059
					],
					[
						36507.3529411765,
						1,
						0
					],
					[
						36066.1764705882,
						1,
						0
					],
					[
						36727.9411764706,
						0,
						220.588235294118
					],
					[
						36507.3529411765,
						4,
						0
					],
					[
						36727.9411764706,
						4,
						441.176470588235
					]
				],
				"altAnim": false,
				"gfSection": false,
				"bpm": 132,
				"mustHitSection": true,
				"changeBPM": false
			},
			{
				"typeOfSection": 0,
				"lengthInSteps": 16,
				"sectionNotes": [
					[
						37389.7058823529,
						6,
						0
					],
					[
						37830.8823529412,
						7,
						110.294117647059
					],
					[
						38161.7647058823,
						5,
						110.294117647059
					],
					[
						37830.8823529412,
						0,
						110.294117647059
					],
					[
						38161.7647058823,
						1,
						0
					],
					[
						38382.3529411765,
						3,
						110.294117647059
					],
					[
						38713.2352941176,
						2,
						0
					],
					[
						37500,
						4,
						110.294117647059
					],
					[
						37058.8235294118,
						7,
						220.588235294118
					]
				],
				"altAnim": false,
				"bpm": 132,
				"mustHitSection": false,
				"changeBPM": false
			},
			{
				"typeOfSection": 0,
				"lengthInSteps": 16,
				"sectionNotes": [
					[
						38823.5294117647,
						5,
						110.294117647059
					],
					[
						39154.4117647059,
						4,
						0
					],
					[
						39154.4117647059,
						2,
						0
					],
					[
						39375,
						1,
						220.588235294118
					],
					[
						40477.9411764706,
						0,
						220.588235294118
					],
					[
						40147.0588235294,
						2,
						0
					],
					[
						40367.6470588235,
						1,
						0
					],
					[
						39375,
						7,
						661.764705882353
					],
					[
						40477.9411764706,
						6,
						110.294117647059
					],
					[
						39705.8823529412,
						0,
						0
					],
					[
						39816.1764705882,
						2,
						0
					],
					[
						40036.7647058824,
						3,
						0
					]
				],
				"altAnim": false,
				"bpm": 132,
				"mustHitSection": true,
				"changeBPM": false
			},
			{
				"typeOfSection": 0,
				"lengthInSteps": 16,
				"sectionNotes": [
					[
						40808.8235294118,
						7,
						220.588235294118
					],
					[
						40808.8235294118,
						1,
						0
					],
					[
						41360.2941176471,
						0,
						0
					],
					[
						41470.5882352941,
						1,
						110.294117647059
					],
					[
						41029.4117647059,
						1,
						110.294117647059
					],
					[
						41801.4705882353,
						2,
						0
					],
					[
						42022.0588235294,
						1,
						220.588235294118
					],
					[
						41801.4705882353,
						6,
						0
					],
					[
						42022.0588235294,
						5,
						441.176470588235
					]
				],
				"altAnim": false,
				"bpm": 132,
				"mustHitSection": false,
				"changeBPM": false
			},
			{
				"typeOfSection": 0,
				"lengthInSteps": 16,
				"sectionNotes": [
					[
						42352.9411764706,
						0,
						0
					],
					[
						42463.2352941177,
						2,
						0
					],
					[
						42683.8235294118,
						3,
						0
					],
					[
						42794.1176470588,
						2,
						220.588235294118
					],
					[
						43125,
						1,
						220.588235294118
					],
					[
						43455.8823529412,
						0,
						0
					],
					[
						43676.4705882353,
						3,
						0
					],
					[
						44007.3529411765,
						1,
						0
					],
					[
						44062.5,
						2,
						220.588235294118
					]
				],
				"altAnim": false,
				"bpm": 132,
				"mustHitSection": false,
				"changeBPM": false
			},
			{
				"typeOfSection": 0,
				"lengthInSteps": 16,
				"sectionNotes": [
					[
						44779.4117647059,
						3,
						0
					],
					[
						45000,
						2,
						0
					],
					[
						45441.1764705882,
						1,
						220.588235294118
					],
					[
						44338.2352941177,
						1,
						0
					],
					[
						44448.5294117647,
						0,
						0
					],
					[
						45110.2941176471,
						3,
						110.294117647059
					],
					[
						45330.8823529412,
						2,
						0
					],
					[
						45772.0588235294,
						0,
						110.294117647059
					]
				],
				"altAnim": false,
				"bpm": 132,
				"mustHitSection": false,
				"changeBPM": false
			},
			{
				"typeOfSection": 0,
				"lengthInSteps": 16,
				"sectionNotes": [
					[
						45992.6470588235,
						2,
						220.588235294118
					],
					[
						46433.8235294118,
						1,
						0
					],
					[
						46323.5294117647,
						1,
						0
					],
					[
						46654.4117647059,
						1,
						0
					],
					[
						46764.705882353,
						0,
						220.588235294118
					],
					[
						47095.5882352941,
						3,
						110.294117647059
					],
					[
						47316.1764705882,
						1,
						220.588235294118
					]
				],
				"altAnim": false,
				"bpm": 132,
				"mustHitSection": false,
				"changeBPM": false
			},
			{
				"typeOfSection": 0,
				"lengthInSteps": 16,
				"sectionNotes": [
					[
						48750,
						0,
						0
					],
					[
						48088.2352941177,
						6,
						0
					],
					[
						48088.2352941177,
						7,
						110.294117647059
					],
					[
						48419.1176470588,
						5,
						0
					],
					[
						48419.1176470588,
						4,
						110.294117647059
					],
					[
						47647.0588235294,
						2,
						0
					],
					[
						47757.3529411765,
						3,
						0
					],
					[
						47977.9411764706,
						0,
						0
					],
					[
						48088.2352941177,
						2,
						220.588235294118
					],
					[
						48419.1176470588,
						3,
						110.294117647059
					],
					[
						48639.705882353,
						1,
						0
					],
					[
						48970.5882352941,
						2,
						0
					],
					[
						49080.8823529412,
						1,
						0
					],
					[
						49301.4705882353,
						0,
						330.882352941176
					]
				],
				"altAnim": false,
				"bpm": 132,
				"mustHitSection": false,
				"changeBPM": false
			},
			{
				"typeOfSection": 0,
				"lengthInSteps": 16,
				"sectionNotes": [
					[
						49742.6470588235,
						3,
						0
					],
					[
						50073.5294117647,
						1,
						0
					],
					[
						50294.1176470588,
						2,
						0
					],
					[
						50404.4117647059,
						1,
						220.588235294118
					],
					[
						50735.2941176471,
						2,
						220.588235294118
					],
					[
						51066.1764705883,
						0,
						110.294117647059
					],
					[
						50294.1176470588,
						4,
						0
					],
					[
						50404.4117647059,
						5,
						220.588235294118
					],
					[
						50735.2941176471,
						7,
						110.294117647059
					],
					[
						50735.2941176471,
						6,
						0
					],
					[
						51066.1764705883,
						5,
						0
					],
					[
						51066.1764705883,
						4,
						110.294117647059
					]
				],
				"altAnim": false,
				"bpm": 132,
				"mustHitSection": false,
				"changeBPM": false
			},
			{
				"typeOfSection": 0,
				"lengthInSteps": 16,
				"sectionNotes": [
					[
						51286.7647058824,
						1,
						0
					],
					[
						51397.0588235294,
						2,
						0
					],
					[
						51617.6470588236,
						3,
						0
					],
					[
						51727.9411764706,
						2,
						0
					],
					[
						51948.5294117647,
						1,
						330.882352941176
					],
					[
						52389.705882353,
						0,
						0
					],
					[
						52720.5882352941,
						2,
						0
					]
				],
				"altAnim": false,
				"bpm": 132,
				"mustHitSection": false,
				"changeBPM": false
			},
			{
				"typeOfSection": 0,
				"lengthInSteps": 16,
				"sectionNotes": [
					[
						52941.1764705883,
						7,
						0
					],
					[
						53051.4705882353,
						6,
						220.588235294118
					],
					[
						52941.1764705883,
						2,
						0
					],
					[
						53051.4705882353,
						1,
						0
					],
					[
						53272.0588235294,
						0,
						0
					],
					[
						53382.3529411765,
						1,
						220.588235294118
					],
					[
						53713.2352941177,
						3,
						220.588235294118
					],
					[
						54044.1176470588,
						2,
						0
					],
					[
						54264.705882353,
						0,
						0
					],
					[
						54595.5882352941,
						3,
						220.588235294118
					]
				],
				"altAnim": false,
				"bpm": 132,
				"mustHitSection": true,
				"changeBPM": false
			},
			{
				"typeOfSection": 0,
				"lengthInSteps": 16,
				"sectionNotes": [
					[
						56029.4117647059,
						1,
						110.294117647059
					],
					[
						55698.5294117647,
						3,
						110.294117647059
					],
					[
						55919.1176470588,
						2,
						0
					],
					[
						56360.2941176471,
						0,
						110.294117647059
					],
					[
						54926.4705882353,
						2,
						0
					],
					[
						55367.6470588236,
						0,
						0
					],
					[
						55036.7647058824,
						1,
						110.294117647059
					],
					[
						55588.2352941177,
						2,
						0
					]
				],
				"altAnim": false,
				"bpm": 132,
				"mustHitSection": true,
				"changeBPM": false
			},
			{
				"typeOfSection": 0,
				"lengthInSteps": 16,
				"sectionNotes": [
					[
						57904.4117647059,
						1,
						220.588235294118
					],
					[
						56580.8823529412,
						1,
						220.588235294118
					],
					[
						56911.7647058824,
						2,
						0
					],
					[
						57022.0588235294,
						3,
						0
					],
					[
						57242.6470588236,
						2,
						0
					],
					[
						57352.9411764706,
						1,
						220.588235294118
					],
					[
						57683.8235294118,
						0,
						110.294117647059
					]
				],
				"altAnim": false,
				"bpm": 132,
				"mustHitSection": true,
				"changeBPM": false
			},
			{
				"typeOfSection": 0,
				"lengthInSteps": 16,
				"sectionNotes": [
					[
						58676.4705882353,
						6,
						0
					],
					[
						58676.4705882353,
						7,
						110.294117647059
					],
					[
						59007.3529411765,
						5,
						0
					],
					[
						59007.3529411765,
						4,
						110.294117647059
					],
					[
						58235.2941176471,
						2,
						0
					],
					[
						58345.5882352941,
						1,
						0
					],
					[
						58566.1764705883,
						3,
						0
					],
					[
						58676.4705882353,
						2,
						0
					],
					[
						58676.4705882353,
						0,
						110.294117647059
					],
					[
						59007.3529411765,
						1,
						110.294117647059
					],
					[
						59007.3529411765,
						2,
						0
					],
					[
						59227.9411764706,
						3,
						0
					],
					[
						59669.1176470589,
						0,
						0
					],
					[
						59338.2352941177,
						2,
						0
					],
					[
						59558.8235294118,
						1,
						0
					],
					[
						59889.705882353,
						2,
						330.882352941176
					]
				],
				"altAnim": false,
				"bpm": 132,
				"mustHitSection": true,
				"changeBPM": false
			},
			{
				"typeOfSection": 0,
				"lengthInSteps": 16,
				"sectionNotes": [
					[
						60330.8823529412,
						3,
						0
					],
					[
						60661.7647058824,
						1,
						0
					],
					[
						60992.6470588236,
						1,
						220.588235294118
					],
					[
						61654.4117647059,
						0,
						110.294117647059
					],
					[
						61323.5294117647,
						7,
						110.294117647059
					],
					[
						61323.5294117647,
						6,
						0
					],
					[
						61654.4117647059,
						5,
						0
					],
					[
						61654.4117647059,
						4,
						110.294117647059
					],
					[
						60882.3529411765,
						0,
						0
					],
					[
						60882.3529411765,
						4,
						330.882352941176
					],
					[
						61323.5294117647,
						3,
						220.588235294118
					],
					[
						61323.5294117647,
						2,
						0
					],
					[
						61654.4117647059,
						1,
						0
					]
				],
				"altAnim": false,
				"bpm": 132,
				"mustHitSection": true,
				"changeBPM": false
			},
			{
				"typeOfSection": 0,
				"lengthInSteps": 16,
				"sectionNotes": [
					[
						61875,
						2,
						0
					],
					[
						61985.2941176471,
						1,
						0
					],
					[
						62205.8823529412,
						2,
						0
					],
					[
						62316.1764705883,
						3,
						0
					],
					[
						62536.7647058824,
						0,
						330.882352941176
					],
					[
						62977.9411764706,
						2,
						0
					],
					[
						63308.8235294118,
						3,
						0
					]
				],
				"sectionBeats": 4,
				"altAnim": false,
				"bpm": 132,
				"mustHitSection": true,
				"changeBPM": false
			},
			{
				"typeOfSection": 0,
				"lengthInSteps": 16,
				"sectionNotes": [
					[
						63529.4117647059,
						1,
						330.882352941176
					],
					[
						63970.5882352942,
						0,
						1102.94117647059
					],
					[
						63529.4117647059,
						5,
						330.882352941176
					],
					[
						63970.5882352942,
						7,
						1102.94117647059
					]
				],
				"sectionBeats": 4,
				"altAnim": false,
				"bpm": 132,
				"mustHitSection": true,
				"changeBPM": false
			},
			{
				"sectionBeats": 4,
				"typeOfSection": 0,
				"lengthInSteps": 16,
				"sectionNotes": [
					[
						66176.4705882353,
						2,
						0
					],
					[
						66286.7647058823,
						3,
						0
					],
					[
						66507.3529411765,
						0,
						0
					],
					[
						66617.6470588235,
						2,
						330.882352941176
					],
					[
						66948.5294117647,
						4,
						110.294117647059
					]
				],
				"altAnim": false,
				"bpm": 132,
				"mustHitSection": true,
				"changeBPM": false
			},
			{
				"typeOfSection": 0,
				"lengthInSteps": 16,
				"sectionNotes": [
					[
						67279.4117647059,
						1,
						0
					],
					[
						67500,
						1,
						110.294117647059
					],
					[
						67830.8823529412,
						2,
						0
					],
					[
						67941.1764705882,
						3,
						0
					],
					[
						68492.6470588235,
						2,
						441.176470588235
					],
					[
						68161.7647058824,
						0,
						0
					]
				],
				"altAnim": false,
				"bpm": 132,
				"mustHitSection": false,
				"changeBPM": false
			},
			{
				"typeOfSection": 0,
				"lengthInSteps": 16,
				"sectionNotes": [
					[
						68823.5294117647,
						6,
						0
					],
					[
						68933.8235294118,
						7,
						0
					],
					[
						69154.4117647059,
						4,
						0
					],
					[
						69264.705882353,
						6,
						330.882352941176
					],
					[
						69595.5882352942,
						0,
						110.294117647059
					],
					[
						70147.0588235294,
						1,
						220.588235294118
					],
					[
						69816.1764705883,
						3,
						0
					],
					[
						69926.4705882353,
						2,
						0
					],
					[
						70477.9411764706,
						0,
						0
					]
				],
				"altAnim": false,
				"bpm": 132,
				"mustHitSection": false,
				"changeBPM": false
			},
			{
				"typeOfSection": 0,
				"lengthInSteps": 16,
				"sectionNotes": [
					[
						70588.2352941177,
						2,
						0
					],
					[
						70919.1176470589,
						2,
						0
					],
					[
						70808.8235294118,
						3,
						0
					],
					[
						71139.705882353,
						1,
						441.176470588235
					],
					[
						71470.5882352942,
						6,
						0
					],
					[
						71580.8823529412,
						7,
						0
					],
					[
						71801.4705882353,
						4,
						0
					],
					[
						72242.6470588236,
						6,
						110.294117647059
					]
				],
				"altAnim": false,
				"bpm": 132,
				"mustHitSection": false,
				"changeBPM": false
			},
			{
				"sectionNotes": [
					[
						72573.5294117647,
						3,
						0
					],
					[
						72794.1176470589,
						2,
						110.294117647059
					],
					[
						73125,
						1,
						0
					],
					[
						73235.2941176471,
						2,
						0
					],
					[
						73455.8823529412,
						1,
						220.588235294118
					],
					[
						73786.7647058824,
						0,
						661.764705882353
					]
				],
				"typeOfSection": 0,
				"lengthInSteps": 16,
				"sectionBeats": 4,
				"altAnim": false,
				"mustHitSection": true,
				"changeBPM": false,
				"bpm": 132
			},
			{
				"lengthInSteps": 16,
				"typeOfSection": 0,
				"sectionNotes": [
					[
						75110.2941176471,
						3,
						0
					],
					[
						75220.5882352942,
						2,
						0
					],
					[
						74117.6470588236,
						5,
						0
					],
					[
						74227.9411764706,
						6,
						0
					],
					[
						74448.5294117647,
						7,
						0
					],
					[
						74558.8235294118,
						6,
						330.882352941176
					],
					[
						74889.705882353,
						2,
						110.294117647059
					],
					[
						75441.1764705883,
						0,
						220.588235294118
					],
					[
						75772.0588235294,
						1,
						0
					]
				],
				"sectionBeats": 4,
				"altAnim": false,
				"bpm": 132,
				"changeBPM": false,
				"mustHitSection": true
			},
			{
				"lengthInSteps": 16,
				"typeOfSection": 0,
				"sectionNotes": [
					[
						75882.3529411765,
						2,
						0
					],
					[
						76102.9411764706,
						1,
						0
					],
					[
						76213.2352941177,
						0,
						0
					],
					[
						76433.8235294118,
						3,
						772.058823529412
					],
					[
						76764.705882353,
						5,
						0
					],
					[
						76875,
						6,
						0
					],
					[
						77095.5882352941,
						7,
						0
					],
					[
						77205.8823529412,
						6,
						220.588235294118
					],
					[
						77536.7647058824,
						4,
						110.294117647059
					],
					[
						77536.7647058824,
						1,
						220.588235294118
					]
				],
				"altAnim": false,
				"bpm": 132,
				"changeBPM": false,
				"mustHitSection": true
			},
			{
				"sectionNotes": [
					[
						77867.6470588235,
						1,
						110.294117647059
					],
					[
						78088.2352941177,
						2,
						110.294117647059
					],
					[
						78419.1176470588,
						1,
						0
					],
					[
						78529.4117647059,
						0,
						110.294117647059
					],
					[
						78860.2941176471,
						3,
						0
					],
					[
						79080.8823529412,
						2,
						220.588235294118
					],
					[
						77867.6470588235,
						6,
						110.294117647059
					],
					[
						78088.2352941177,
						4,
						220.588235294118
					],
					[
						78419.1176470588,
						6,
						0
					],
					[
						78529.4117647059,
						7,
						110.294117647059
					],
					[
						78860.2941176471,
						6,
						0
					],
					[
						79080.8823529412,
						5,
						661.764705882353
					]
				],
				"typeOfSection": 0,
				"lengthInSteps": 16,
				"altAnim": false,
				"mustHitSection": false,
				"changeBPM": false,
				"bpm": 132
			},
			{
				"sectionNotes": [
					[
						79411.7647058824,
						1,
						0
					],
					[
						79522.0588235294,
						2,
						0
					],
					[
						79742.6470588235,
						3,
						0
					],
					[
						79852.9411764706,
						2,
						220.588235294118
					],
					[
						80183.8235294118,
						0,
						220.588235294118
					],
					[
						80514.705882353,
						2,
						110.294117647059
					],
					[
						80735.2941176471,
						1,
						110.294117647059
					],
					[
						81066.1764705883,
						0,
						0
					],
					[
						80183.8235294118,
						6,
						220.588235294118
					],
					[
						80514.705882353,
						5,
						110.294117647059
					],
					[
						80735.2941176471,
						4,
						110.294117647059
					],
					[
						81066.1764705883,
						7,
						0
					]
				],
				"typeOfSection": 0,
				"lengthInSteps": 16,
				"altAnim": false,
				"mustHitSection": false,
				"changeBPM": false,
				"bpm": 132
			},
			{
				"lengthInSteps": 16,
				"typeOfSection": 0,
				"sectionNotes": [
					[
						81176.4705882353,
						3,
						0
					],
					[
						81397.0588235294,
						2,
						0
					],
					[
						81507.3529411765,
						1,
						0
					],
					[
						81727.9411764706,
						2,
						661.764705882353
					],
					[
						81176.4705882353,
						5,
						330.882352941176
					],
					[
						81727.9411764706,
						4,
						220.588235294118
					],
					[
						82058.8235294118,
						6,
						0
					],
					[
						82169.1176470588,
						7,
						0
					],
					[
						82389.705882353,
						4,
						0
					],
					[
						82500,
						6,
						0
					],
					[
						82830.8823529412,
						7,
						110.294117647059
					],
					[
						82830.8823529412,
						0,
						220.588235294118
					]
				],
				"altAnim": false,
				"bpm": 132,
				"changeBPM": false,
				"mustHitSection": false
			},
			{
				"sectionNotes": [
					[
						83161.7647058824,
						1,
						110.294117647059
					],
					[
						83382.3529411765,
						2,
						110.294117647059
					],
					[
						83161.7647058823,
						7,
						110.294117647059
					],
					[
						83382.3529411765,
						6,
						330.882352941176
					],
					[
						83823.5294117647,
						5,
						110.294117647059
					],
					[
						84154.4117647059,
						4,
						0
					],
					[
						84375,
						7,
						661.764705882353
					],
					[
						83713.2352941177,
						3,
						0
					],
					[
						83823.5294117647,
						1,
						110.294117647059
					],
					[
						84154.4117647059,
						0,
						0
					],
					[
						84375,
						1,
						220.588235294118
					]
				],
				"typeOfSection": 0,
				"lengthInSteps": 16,
				"altAnim": false,
				"mustHitSection": true,
				"changeBPM": false,
				"bpm": 132
			},
			{
				"lengthInSteps": 16,
				"typeOfSection": 0,
				"sectionNotes": [
					[
						85808.8235294118,
						2,
						110.294117647059
					],
					[
						84705.8823529412,
						2,
						0
					],
					[
						84816.1764705882,
						1,
						0
					],
					[
						85147.0588235294,
						3,
						220.588235294118
					],
					[
						85036.7647058823,
						2,
						0
					],
					[
						85477.9411764706,
						1,
						220.588235294118
					],
					[
						86029.4117647059,
						0,
						110.294117647059
					],
					[
						86360.2941176471,
						3,
						0
					],
					[
						85477.9411764706,
						5,
						220.588235294118
					],
					[
						85808.8235294118,
						4,
						110.294117647059
					],
					[
						86029.4117647059,
						7,
						110.294117647059
					],
					[
						86360.2941176471,
						6,
						0
					]
				],
				"altAnim": false,
				"gfSection": false,
				"bpm": 132,
				"changeBPM": false,
				"mustHitSection": true
			},
			{
				"lengthInSteps": 16,
				"typeOfSection": 0,
				"sectionNotes": [
					[
						86691.1764705882,
						2,
						0
					],
					[
						86470.5882352941,
						5,
						330.882352941176
					],
					[
						87022.0588235294,
						4,
						220.588235294118
					],
					[
						86470.5882352941,
						1,
						0
					],
					[
						86801.4705882353,
						3,
						0
					],
					[
						87022.0588235294,
						1,
						661.764705882353
					],
					[
						87352.9411764706,
						5,
						0
					],
					[
						87463.2352941176,
						6,
						0
					],
					[
						87683.8235294118,
						7,
						0
					],
					[
						87794.1176470588,
						6,
						220.588235294118
					],
					[
						88125,
						4,
						0
					]
				],
				"altAnim": false,
				"gfSection": false,
				"bpm": 132,
				"changeBPM": false,
				"mustHitSection": true
			},
			{
				"sectionBeats": 4,
				"sectionNotes": [
					[
						88345.5882352941,
						1,
						0
					],
					[
						88455.8823529412,
						3,
						110.294117647059
					],
					[
						88676.4705882353,
						2,
						0
					],
					[
						89338.2352941176,
						2,
						0
					],
					[
						89448.5294117647,
						3,
						0
					],
					[
						89779.4117647059,
						0,
						0
					],
					[
						89007.3529411765,
						0,
						0
					],
					[
						89062.5,
						1,
						220.588235294118
					]
				],
				"typeOfSection": 0,
				"gfSection": false,
				"altAnim": false,
				"mustHitSection": false,
				"changeBPM": false,
				"bpm": 132
			},
			{
				"sectionBeats": 4,
				"sectionNotes": [
					[
						90000,
						3,
						0
					],
					[
						90110.294117647,
						2,
						110.294117647059
					],
					[
						90330.8823529412,
						0,
						0
					],
					[
						90441.1764705882,
						1,
						220.588235294118
					],
					[
						90772.0588235294,
						2,
						110.294117647059
					],
					[
						90992.6470588235,
						0,
						220.588235294118
					],
					[
						91323.5294117647,
						3,
						0
					],
					[
						91433.8235294117,
						1,
						0
					],
					[
						91654.4117647059,
						2,
						0
					]
				],
				"typeOfSection": 0,
				"gfSection": false,
				"altAnim": false,
				"mustHitSection": false,
				"changeBPM": false,
				"bpm": 100
			},
			{
				"typeOfSection": 0,
				"sectionNotes": [
					[
						91764.7058823529,
						3,
						220.588235294118
					],
					[
						92095.5882352941,
						2,
						0
					],
					[
						92316.1764705882,
						1,
						220.588235294118
					],
					[
						92647.0588235294,
						2,
						0
					],
					[
						92757.3529411764,
						3,
						0
					],
					[
						93088.2352941176,
						2,
						0
					],
					[
						92977.9411764706,
						0,
						0
					],
					[
						93088.2352941176,
						3,
						110.294117647059
					],
					[
						93419.1176470588,
						1,
						0
					],
					[
						93419.1176470588,
						0,
						110.294117647059
					],
					[
						93088.2352941176,
						6,
						0
					],
					[
						93088.2352941176,
						7,
						110.294117647059
					],
					[
						93419.1176470588,
						5,
						0
					],
					[
						93419.1176470588,
						4,
						110.294117647059
					]
				],
				"sectionBeats": 4,
				"altAnim": false,
				"gfSection": false,
				"bpm": 100,
				"changeBPM": false,
				"mustHitSection": false
			},
			{
				"typeOfSection": 0,
				"sectionNotes": [
					[
						93639.7058823529,
						1,
						0
					],
					[
						93750,
						1,
						0
					],
					[
						93970.5882352941,
						2,
						0
					],
					[
						94080.8823529412,
						3,
						0
					],
					[
						94301.4705882353,
						1,
						0
					],
					[
						94301.4705882353,
						0,
						330.882352941176
					],
					[
						94742.6470588235,
						2,
						0
					],
					[
						95073.5294117647,
						3,
						110.294117647059
					],
					[
						93639.7058823529,
						7,
						0
					],
					[
						93750,
						6,
						0
					],
					[
						94080.8823529412,
						6,
						0
					],
					[
						93970.5882352941,
						5,
						0
					],
					[
						94301.4705882353,
						5,
						0
					],
					[
						94301.4705882353,
						4,
						330.882352941176
					],
					[
						94742.6470588235,
						7,
						0
					],
					[
						95073.5294117647,
						5,
						110.294117647059
					]
				],
				"sectionBeats": 4,
				"altAnim": false,
				"gfSection": false,
				"bpm": 100,
				"changeBPM": false,
				"mustHitSection": true
			},
			{
				"typeOfSection": 0,
				"sectionNotes": [
					[
						95294.1176470588,
						6,
						0
					],
					[
						95404.4117647059,
						5,
						220.588235294118
					],
					[
						95294.1176470588,
						2,
						0
					],
					[
						95404.4117647059,
						1,
						220.588235294118
					],
					[
						95735.294117647,
						0,
						110.294117647059
					],
					[
						95735.294117647,
						3,
						0
					],
					[
						96066.1764705882,
						3,
						110.294117647059
					],
					[
						96397.0588235294,
						0,
						0
					],
					[
						96617.6470588235,
						2,
						0
					],
					[
						96727.9411764706,
						1,
						0
					],
					[
						96948.5294117647,
						0,
						330.882352941176
					],
					[
						95735.294117647,
						6,
						0
					],
					[
						95735.294117647,
						7,
						110.294117647059
					],
					[
						96066.1764705882,
						5,
						0
					],
					[
						96066.1764705882,
						4,
						110.294117647059
					],
					[
						96286.7647058823,
						6,
						0
					],
					[
						96397.0588235294,
						5,
						0
					],
					[
						96617.6470588235,
						6,
						0
					],
					[
						96727.9411764706,
						7,
						0
					],
					[
						96948.5294117647,
						4,
						330.882352941176
					],
					[
						96066.1764705882,
						2,
						0
					],
					[
						96286.7647058823,
						1,
						0
					]
				],
				"sectionBeats": 4,
				"altAnim": false,
				"gfSection": false,
				"bpm": 100,
				"changeBPM": false,
				"mustHitSection": false
			},
			{
				"typeOfSection": 0,
				"sectionNotes": [
					[
						97389.7058823529,
						2,
						0
					],
					[
						97389.7058823529,
						5,
						0
					],
					[
						97720.5882352941,
						1,
						110.294117647059
					],
					[
						97941.1764705882,
						2,
						0
					],
					[
						98051.4705882353,
						1,
						0
					],
					[
						98272.0588235294,
						0,
						0
					],
					[
						98382.3529411764,
						1,
						110.294117647059
					],
					[
						98713.2352941176,
						3,
						0
					],
					[
						97720.5882352941,
						6,
						110.294117647059
					],
					[
						97941.1764705882,
						7,
						0
					],
					[
						98051.4705882353,
						6,
						220.588235294118
					]
				],
				"sectionBeats": 4,
				"altAnim": false,
				"gfSection": false,
				"bpm": 100,
				"changeBPM": false,
				"mustHitSection": true
			},
			{
				"typeOfSection": 0,
				"sectionNotes": [
					[
						98933.8235294117,
						2,
						0
					],
					[
						99044.1176470588,
						1,
						0
					],
					[
						99264.7058823529,
						0,
						110.294117647059
					],
					[
						99926.4705882353,
						1,
						0
					],
					[
						100036.764705882,
						2,
						110.294117647059
					],
					[
						100367.647058823,
						1,
						0
					],
					[
						99595.5882352941,
						3,
						0
					],
					[
						99650.7352941176,
						2,
						220.588235294118
					]
				],
				"sectionBeats": 4,
				"altAnim": false,
				"gfSection": false,
				"bpm": 100,
				"changeBPM": false,
				"mustHitSection": true
			},
			{
				"sectionBeats": 4,
				"sectionNotes": [
					[
						100588.235294118,
						0,
						0
					],
					[
						100919.117647059,
						3,
						0
					],
					[
						100698.529411765,
						2,
						110.294117647059
					],
					[
						101029.411764706,
						1,
						0
					],
					[
						101360.294117647,
						0,
						0
					],
					[
						101580.882352941,
						1,
						220.588235294118
					],
					[
						101911.764705882,
						2,
						0
					],
					[
						102022.058823529,
						2,
						0
					],
					[
						102242.647058823,
						3,
						0
					]
				],
				"typeOfSection": 0,
				"gfSection": false,
				"altAnim": false,
				"mustHitSection": true,
				"changeBPM": false,
				"bpm": 100
			},
			{
				"sectionBeats": 4,
				"sectionNotes": [
					[
						102352.941176471,
						0,
						220.588235294118
					],
					[
						102683.823529412,
						2,
						0
					],
					[
						102904.411764706,
						1,
						220.588235294118
					],
					[
						103235.294117647,
						0,
						0
					],
					[
						103345.588235294,
						2,
						0
					],
					[
						103566.176470588,
						3,
						0
					],
					[
						103676.470588235,
						1,
						0
					],
					[
						103676.470588235,
						0,
						110.294117647059
					],
					[
						104007.352941176,
						2,
						0
					],
					[
						104007.352941176,
						3,
						110.294117647059
					],
					[
						103676.470588235,
						5,
						0
					],
					[
						103676.470588235,
						4,
						110.294117647059
					],
					[
						104007.352941176,
						6,
						0
					],
					[
						104007.352941176,
						7,
						110.294117647059
					]
				],
				"typeOfSection": 0,
				"gfSection": false,
				"altAnim": false,
				"mustHitSection": true,
				"changeBPM": false,
				"bpm": 136
			},
			{
				"sectionBeats": 4,
				"sectionNotes": [
					[
						104227.941176471,
						1,
						0
					],
					[
						104338.235294118,
						1,
						0
					],
					[
						104558.823529412,
						2,
						0
					],
					[
						104669.117647059,
						3,
						0
					],
					[
						104889.705882353,
						1,
						0
					],
					[
						104889.705882353,
						0,
						330.882352941176
					],
					[
						105330.882352941,
						2,
						0
					],
					[
						105661.764705882,
						3,
						110.294117647059
					],
					[
						104227.941176471,
						7,
						0
					],
					[
						104338.235294118,
						6,
						0
					],
					[
						104669.117647059,
						6,
						0
					],
					[
						104558.823529412,
						5,
						0
					],
					[
						104889.705882353,
						5,
						0
					],
					[
						104889.705882353,
						4,
						330.882352941176
					],
					[
						105330.882352941,
						7,
						0
					],
					[
						105661.764705882,
						5,
						110.294117647059
					]
				],
				"typeOfSection": 0,
				"gfSection": false,
				"altAnim": false,
				"mustHitSection": true,
				"changeBPM": false,
				"bpm": 136
			},
			{
				"sectionBeats": 4,
				"sectionNotes": [
					[
						105882.352941176,
						6,
						0
					],
					[
						105992.647058824,
						5,
						220.588235294118
					],
					[
						105882.352941176,
						2,
						0
					],
					[
						105992.647058824,
						1,
						220.588235294118
					],
					[
						106323.529411765,
						0,
						110.294117647059
					],
					[
						106323.529411765,
						3,
						0
					],
					[
						106654.411764706,
						3,
						110.294117647059
					],
					[
						106985.294117647,
						0,
						0
					],
					[
						107205.882352941,
						2,
						0
					],
					[
						107316.176470588,
						1,
						0
					],
					[
						107536.764705882,
						0,
						330.882352941176
					],
					[
						106323.529411765,
						6,
						0
					],
					[
						106323.529411765,
						7,
						110.294117647059
					],
					[
						106654.411764706,
						5,
						0
					],
					[
						106654.411764706,
						4,
						110.294117647059
					],
					[
						106875,
						6,
						0
					],
					[
						106985.294117647,
						5,
						0
					],
					[
						107205.882352941,
						6,
						0
					],
					[
						107316.176470588,
						7,
						0
					],
					[
						107536.764705882,
						4,
						330.882352941176
					],
					[
						106654.411764706,
						2,
						0
					],
					[
						106875,
						1,
						0
					]
				],
				"typeOfSection": 0,
				"gfSection": false,
				"altAnim": false,
				"mustHitSection": true,
				"changeBPM": false,
				"bpm": 136
			},
			{
				"sectionBeats": 4,
				"sectionNotes": [
					[
						107977.941176471,
						2,
						0
					],
					[
						107977.941176471,
						5,
						0
					],
					[
						108308.823529412,
						1,
						110.294117647059
					],
					[
						108529.411764706,
						2,
						0
					],
					[
						108308.823529412,
						6,
						110.294117647059
					],
					[
						108639.705882353,
						3,
						220.588235294118
					],
					[
						108970.588235294,
						0,
						1433.82352941176
					],
					[
						108970.588235294,
						1,
						0
					],
					[
						108529.411764706,
						5,
						0
					],
					[
						108639.705882353,
						4,
						220.588235294118
					],
					[
						108970.588235294,
						6,
						0
					],
					[
						108970.588235294,
						7,
						1213.23529411765
					]
				],
				"typeOfSection": 0,
				"gfSection": false,
				"altAnim": false,
				"mustHitSection": true,
				"changeBPM": false,
				"bpm": 136
			},
			{
				"sectionBeats": 4,
				"sectionNotes": [],
				"typeOfSection": 0,
				"gfSection": false,
				"altAnim": false,
				"mustHitSection": true,
				"changeBPM": false,
				"bpm": 136
			},
			{
				"sectionBeats": 4,
				"sectionNotes": [],
				"typeOfSection": 0,
				"gfSection": false,
				"altAnim": false,
				"mustHitSection": true,
				"changeBPM": false,
				"bpm": 136
			},
			{
				"sectionBeats": 4,
				"sectionNotes": [],
				"typeOfSection": 0,
				"gfSection": false,
				"altAnim": false,
				"mustHitSection": true,
				"changeBPM": false,
				"bpm": 136
			},
			{
				"sectionBeats": 4,
				"sectionNotes": [],
				"typeOfSection": 0,
				"gfSection": false,
				"altAnim": false,
				"mustHitSection": true,
				"changeBPM": false,
				"bpm": 136
			},
			{
				"sectionBeats": 4,
				"sectionNotes": [],
				"typeOfSection": 0,
				"gfSection": false,
				"altAnim": false,
				"mustHitSection": true,
				"changeBPM": false,
				"bpm": 136
			},
			{
				"sectionBeats": 4,
				"sectionNotes": [],
				"typeOfSection": 0,
				"gfSection": false,
				"altAnim": false,
				"mustHitSection": true,
				"changeBPM": false,
				"bpm": 136
			},
			{
				"sectionBeats": 4,
				"sectionNotes": [],
				"typeOfSection": 0,
				"gfSection": false,
				"altAnim": false,
				"mustHitSection": true,
				"changeBPM": false,
				"bpm": 136
			},
			{
				"gfSection": false,
				"lengthInSteps": 16,
				"altAnim": false,
				"typeOfSection": 0,
				"sectionNotes": [],
				"bpm": 136,
				"changeBPM": false,
				"mustHitSection": true
			}
		],
		"player2": "eggman",
		"player3": null,
		"song": "metropolis",
		"needsVoices": true,
		"validScore": true,
		"sections": 0,
		"stage": "metropolise",
		"bpm": 136,
		"speed": 2.9
	}
}